gdoc_down/__init__.py
gdoc_down/__main__.py
gdoc_down/_version.py
gdoc_down/client.json
gdoc_down/core.py
gdoc_down-0.0.10.dist-info/LICENSE
gdoc_down-0.0.10.dist-info/METADATA
gdoc_down-0.0.10.dist-info/WHEEL
gdoc_down-0.0.10.dist-info/entry_points.txt
gdoc_down-0.0.10.dist-info/top_level.txt
gdoc_down-0.0.10.dist-info/RECORD
