Metadata-Version: 2.1
Name: gdoc-down
Version: 0.0.10
Summary: Download Google documents to files
Home-page: https://github.com/KarrLab/gdoc_down
Author: Karr Lab
Author-email: info@karrlab.org
License: MIT
Download-URL: https://github.com/KarrLab/gdoc_down
Keywords: Google documents drive download latex tex html pdf docx
Platform: UNKNOWN
Classifier: Development Status :: 3 - Alpha
Classifier: Intended Audience :: End Users/Desktop
Classifier: Topic :: Communications :: File Sharing
Classifier: Topic :: Office/Business :: Office Suites
Classifier: Topic :: Utilities
Classifier: License :: OSI Approved :: MIT License
Classifier: Programming Language :: Python
Requires-Dist: beautifulsoup4
Requires-Dist: cement (>=3.0.0)
Requires-Dist: google-api-python-client
Requires-Dist: oauth2client
Provides-Extra: all
Requires-Dist: docx ; extra == 'all'
Requires-Dist: mock ; extra == 'all'
Requires-Dist: odfpy ; extra == 'all'
Requires-Dist: pypdf2 ; extra == 'all'
Requires-Dist: python-docx ; extra == 'all'
Requires-Dist: rtf2xml ; extra == 'all'
Requires-Dist: sphinx (>=1.8) ; extra == 'all'
Requires-Dist: sphinx-fontawesome ; extra == 'all'
Requires-Dist: sphinx-rtd-theme (>=0.4.2) ; extra == 'all'
Requires-Dist: sphinxcontrib-addmetahtml (>=0.1.1) ; extra == 'all'
Requires-Dist: sphinxcontrib-bibtex ; extra == 'all'
Requires-Dist: sphinxcontrib-googleanalytics (>=0.1.1) ; extra == 'all'
Requires-Dist: sphinxcontrib-spelling ; extra == 'all'
Requires-Dist: sphinxprettysearchresults ; extra == 'all'
Provides-Extra: docs
Requires-Dist: sphinx (>=1.8) ; extra == 'docs'
Requires-Dist: sphinx-fontawesome ; extra == 'docs'
Requires-Dist: sphinx-rtd-theme (>=0.4.2) ; extra == 'docs'
Requires-Dist: sphinxcontrib-addmetahtml (>=0.1.1) ; extra == 'docs'
Requires-Dist: sphinxcontrib-bibtex ; extra == 'docs'
Requires-Dist: sphinxcontrib-googleanalytics (>=0.1.1) ; extra == 'docs'
Requires-Dist: sphinxcontrib-spelling ; extra == 'docs'
Requires-Dist: sphinxprettysearchresults ; extra == 'docs'
Provides-Extra: tests
Requires-Dist: docx ; extra == 'tests'
Requires-Dist: mock ; extra == 'tests'
Requires-Dist: odfpy ; extra == 'tests'
Requires-Dist: pypdf2 ; extra == 'tests'
Requires-Dist: python-docx ; extra == 'tests'
Requires-Dist: rtf2xml ; extra == 'tests'
